mdpong/__init__.py
mdpong/__main__.py
mdpong/mdpong.py
mdpong-1.1.2.dist-info/METADATA
mdpong-1.1.2.dist-info/WHEEL
mdpong-1.1.2.dist-info/entry_points.txt
mdpong-1.1.2.dist-info/top_level.txt
mdpong-1.1.2.dist-info/RECORD
