Metadata-Version: 2.4
Name: mdpong
Version: 1.1.2
Summary: A modern Pong game built in Python Turtle Graphics
Author-email: Maalek Darkal <maalekdarkal@gmail.com>
License: MIT
Project-URL: Homepage, https://github.com/MaalekDarkalX1/pong
Classifier: Programming Language :: Python :: 3
Classifier: License :: OSI Approved :: MIT License
Classifier: Operating System :: OS Independent
Classifier: Topic :: Games/Entertainment
Requires-Python: >=3.8
